{
  "instance": {
    "num_nodes": 66,
    "team_size": 2,
    "max_route_distance": 45.0,
    "start_depot": 0,
    "end_depot": 65
  },
  "objective": {
    "total_score": 1210.0
  },
  "performance": {
    "cpu_time_seconds": 1.2681953999999678,
    "iterations": 20,
    "iterations_to_convergence": 17,
    "last_improvement_iteration": 17,
    "stagnation_iterations": 3,
    "accepted_worse_moves": 12,
    "restarts_performed": 1,
    "num_lp_solves": null,
    "num_labels_generated": null
  },
  "routes": [
    {
      "route_index": 1,
      "nodes": [
        0,
        21,
        20,
        12,
        13,
        14,
        15,
        16,
        8,
        7,
        6,
        5,
        4,
        3,
        2,
        1,
        9,
        17,
        25,
        34,
        35,
        36,
        65
      ],
      "score": 595.0,
      "length": 44.639043517063335
    },
    {
      "route_index": 2,
      "nodes": [
        0,
        28,
        27,
        26,
        33,
        41,
        49,
        57,
        58,
        59,
        60,
        61,
        62,
        63,
        64,
        56,
        48,
        47,
        55,
        54,
        53,
        45,
        65
      ],
      "score": 615.0,
      "length": 44.639043517063335
    }
  ],
  "dataset": "chao",
  "instance_name": "p5.2.r.txt",
  "run_seed": 77007,
  "run_index": 0
}